analyses/__init__.py
analyses/analyze_frame.py
analyses/awakeBones.py
analyses/awakeMeat.py
analyses/errStuff.py
analyses/frame_analysis.py
analyses/gaussStuff.py
analyses/peak_finder.py
examples/__init__.py
examples/tests.py
examples/virtual_device_example.py
japc_support/AwkCmra.py
japc_support/__init__.py
ntupling/TimingCheck.py
ntupling/__init__.py
ntupling/bunchRotationStatus.py
ntupling/createFileMap.py
ntupling/createNtuple.py
ntupling/cutParser.py
ntupling/cutParserDefines.py
ntupling/getFileMap.py
ntupling/returnAlignmentData.py
ntupling/returnBranchData.py
ntupling/returnCamProps.py
ntupling/returnFileData.py
ntupling/returnFileMap.py
ntupling/returnGoodData.py
ntupling/returnPlasmaDensity.py
plotting_tools/Laser_gui.py
plotting_tools/Plotter_gui.py
plotting_tools/__init__.py
plotting_tools/awakeIMClass.py
plotting_tools/awakeScanGUI.py
plotting_tools/awakerunPlotsStreak.py
plotting_tools/awakerunPlotsStreakBI.py
plotting_tools/fabianPlots.py
plotting_tools/felipeBI.py
plotting_tools/felipePlots.py
plotting_tools/view_streak.py
utilities/__init__.py
utilities/custom_cmap.py
utilities/returnData.py
utilities/setup.py
AWAKE_ANALYSIS_TOOLS-0.0.2.dist-info/LICENSE
AWAKE_ANALYSIS_TOOLS-0.0.2.dist-info/METADATA
AWAKE_ANALYSIS_TOOLS-0.0.2.dist-info/WHEEL
AWAKE_ANALYSIS_TOOLS-0.0.2.dist-info/top_level.txt
AWAKE_ANALYSIS_TOOLS-0.0.2.dist-info/RECORD
